setup.cfg
setup.py
githubcity/__init__.py
githubcity/ghcity.py
githubcity/ghregion.py
githubcity/ghuser.py
githubcity.egg-info/PKG-INFO
githubcity.egg-info/SOURCES.txt
githubcity.egg-info/dependency_links.txt
githubcity.egg-info/requires.txt
githubcity.egg-info/top_level.txt