Metadata-Version: 1.0
Name: githubcity
Version: 1.0.6
Summary: GitHub city ranking creator
Home-page: https://github.com/iblancasa/GitHubCity
Author: Israel Blancas @iblancasa
Author-email: iblancasa@gmail.com
License: MIT
Keywords: github,ranking,data,api
Platform: UNKNOWN
